{"ok":true,"areaId":"5a6b82fb2a64a2e50f2ee8fd","areaName":"a8883580's home","areaKey":"rr5a6b82fb665dc4e50fdadd37","areaCreatorId":"5a6b82fb2a64a2e50f2ee8fc","isPrivate":false,"isZeroGravity":false,"hasFloatingDust":false,"isCopyable":false,"onlyOwnerSetsLocks":false,"isExcluded":false,"environmentChangersJSON":"{\"environmentChangers\":[]}","requestorIsEditor":false,"requestorIsListEditor":false,"requestorIsOwner":false,"placements":[{"Id":"5a6b82fb665dc4e50fdadd38","Tid":"000000000000000000000001","P":{"x":0.62715387344,"y":-0.275627732,"z":0.321439146995},"R":{"x":0,"y":0,"z":0}}],"serveTime":25}