{"ok":true,"areaId":"6028a9bf8710e2055373207b","areaName":"cdesmondd's home","areaKey":"rr6028a9bf5ce81305537b5c6c","areaCreatorId":"6028a9b88710e2055373207a","isPrivate":false,"isZeroGravity":false,"hasFloatingDust":false,"isCopyable":false,"onlyOwnerSetsLocks":false,"isExcluded":false,"environmentChangersJSON":"{\"environmentChangers\":[]}","requestorIsEditor":false,"requestorIsListEditor":false,"requestorIsOwner":false,"placements":[{"Id":"6028a9d05ce81305537b5c6d","Tid":"000000000000000000000001","P":{"x":0.62715387344,"y":-0.275627732,"z":0.321439146995},"R":{"x":0,"y":0,"z":0},"A":[1]}],"serveTime":16}