{"thingDefinitions":[{"id":"655e526f35ac821583ea11c7","def":"{\"v\":9,\"a\":[7,18,21,49],\"p\":[{\"b\":86,\"t\":2,\"a\":[11,23],\"t1\":23,\"s\":[{\"p\":[0,0,0],\"r\":[0,0,0],\"s\":[1.044841,1.044846,1.044841],\"c\":[0,0,0],\"b\":[\"when starts then become next in 1s\"],\"t1\":{\"c\":[1,1,1],\"x\":0.5920963,\"y\":0.5920662,\"a\":0.25,\"m\":0.3927059,\"n\":0.2150025,\"r\":0,\"g\":1,\"o\":0,\"t\":0.5,\"e\":0.5}},{\"p\":[0,0,0],\"r\":[0,0,0],\"s\":[1.044841,1.044846,1.044841],\"c\":[0,0,0],\"b\":[\"when starts then become untweened previous in 0.0s\"],\"t1\":{\"c\":[1,1,1],\"x\":0.5920963,\"y\":0.5920662,\"a\":0.25,\"m\":0.3927059,\"n\":0.2150025,\"r\":0,\"g\":1,\"o\":0.9732513,\"t\":0.5,\"e\":0.5}},{\"p\":[0,0,0],\"r\":[0,0,0],\"s\":[1.044841,1.044846,1.044841],\"c\":[0,0,0],\"t1\":{\"c\":[1,1,1],\"x\":0.5920963,\"y\":0.5920662,\"a\":0.25,\"m\":0.3927059,\"n\":0.2150025,\"r\":0,\"g\":0,\"o\":0.5,\"t\":0.5,\"e\":0.5}}]},{\"b\":86,\"t\":21,\"a\":[11],\"s\":[{\"p\":[-4.768372E-07,0.07197023,8.270144E-07],\"r\":[0,0,0],\"s\":[1.044879,1.044861,1.044895],\"c\":[1,0,0],\"b\":[\"when starts then become untweened next in 0.01s\"]},{\"p\":[-4.768372E-07,0.07197023,8.270144E-07],\"r\":[0,0,0],\"s\":[1.044879,1.044861,1.044895],\"c\":[0.1142857,0,1],\"b\":[\"when starts then become untweened next in 0.01s\"]},{\"p\":[-4.768372E-07,0.07197023,8.270144E-07],\"r\":[0,0,0],\"s\":[1.044879,1.044861,1.044895],\"c\":[0.1142856,1,0],\"b\":[\"when starts then become untweened next in 0.01s\"]}]}]}"},{"id":"655e52d52ae71514cd3f0d9d","def":"{\"v\":9,\"p\":[{\"a\":[1,36],\"s\":[{\"p\":[0,0,0],\"r\":[0,0,0],\"s\":[0.1750003,0.1750003,0.1750004],\"c\":[1,1,1],\"b\":[\"when starts then show web https://www.youtube.com/watch?v=qZkZWbpzqKE , then become next in 300s\"]},{\"p\":[0,0,0],\"r\":[0,0,0],\"s\":[0.1750003,0.1750003,0.1750004],\"c\":[1,1,1],\"b\":[\"when starts then show web https://www.youtube.com/watch?v=qZkZWbpzqKE , then become next in 300s\"]}]}]}"},{"id":"655e497e2ae71514cd3f0d98","def":"{\"v\":9,\"p\":[{\"a\":[1],\"s\":[{\"p\":[0,0,0],\"r\":[0,0,0],\"s\":[0.1750003,0.1750003,0.1750004],\"c\":[1,1,1],\"b\":[\"when starts then show web https://www.youtube.com/watch?v=nQoU_2ElF14\"]}]}]}"},{"id":"655e4d11baa2b214c006535a","def":"{\"n\":\"tptp\",\"v\":9,\"a\":[31,48],\"p\":[{\"s\":[{\"p\":[0,0,0],\"r\":[4.268868E-07,-7.951387E-16,-2.134434E-07],\"s\":[0.1750006,0.1750005,0.1750009],\"c\":[1,1,1],\"b\":[\"when starts then send nearby onto tptp , then become next in 0.0s\"]},{\"p\":[0,0,0],\"r\":[4.268868E-07,-7.951387E-16,-2.134434E-07],\"s\":[0.1750006,0.1750005,0.1750009],\"c\":[1,1,1],\"b\":[\"when starts then send nearby onto tptp , then become next in 0.0s\"]}]}]}"},{"id":"655e5231fa6d7805c7ff3ecf","def":"{\"v\":9,\"a\":[7,18,21,49],\"p\":[{\"b\":86,\"t\":2,\"a\":[11,23],\"t1\":23,\"s\":[{\"p\":[0,0,0],\"r\":[0,0,0],\"s\":[1.044841,1.044846,1.044841],\"c\":[0,0,0],\"b\":[\"when starts then become next in 1s\"],\"t1\":{\"c\":[1,1,1],\"x\":0.5920963,\"y\":0.5920662,\"a\":0.25,\"m\":0.3927059,\"n\":0.2150025,\"r\":0,\"g\":1,\"o\":0,\"t\":0.5,\"e\":0.5}},{\"p\":[0,0,0],\"r\":[0,0,0],\"s\":[1.044841,1.044846,1.044841],\"c\":[0,0,0],\"b\":[\"when starts then become untweened previous in 0.0s\"],\"t1\":{\"c\":[1,1,1],\"x\":0.5920963,\"y\":0.5920662,\"a\":0.25,\"m\":0.3927059,\"n\":0.2150025,\"r\":0,\"g\":1,\"o\":0.9732513,\"t\":0.5,\"e\":0.5}},{\"p\":[0,0,0],\"r\":[0,0,0],\"s\":[1.044841,1.044846,1.044841],\"c\":[0,0,0],\"t1\":{\"c\":[1,1,1],\"x\":0.5920963,\"y\":0.5920662,\"a\":0.25,\"m\":0.3927059,\"n\":0.2150025,\"r\":0,\"g\":0,\"o\":0.5,\"t\":0.5,\"e\":0.5}}]},{\"b\":86,\"t\":21,\"a\":[11],\"s\":[{\"p\":[-4.768372E-07,0.07197023,8.270144E-07],\"r\":[0,0,0],\"s\":[1.044879,1.044861,1.044895],\"c\":[1,0,0],\"b\":[\"when starts then become untweened next in 0.01s\"]},{\"p\":[-4.768372E-07,0.07197023,8.270144E-07],\"r\":[0,0,0],\"s\":[1.044879,1.044861,1.044895],\"c\":[0.1142857,0,1],\"b\":[\"when starts then become untweened next in 0.01s\"]},{\"p\":[-4.768372E-07,0.07197023,8.270144E-07],\"r\":[0,0,0],\"s\":[1.044879,1.044861,1.044895],\"c\":[0.1142856,1,0],\"b\":[\"when starts then become untweened next in 0.01s\"]}]}]}"},{"id":"655e50c32ae71514cd3f0d9b","def":"{\"v\":9,\"a\":[7,18,41],\"p\":[{\"b\":5,\"a\":[12],\"s\":[{\"p\":[0,0,0],\"r\":[0,0,0],\"s\":[4.704259,1.775563,0.1365793],\"c\":[1,1,1],\"b\":[\"when starts then set constant rotation to 0 -600 0\",\"when touched then show areas \"]}]}]}"},{"id":"655e50acf728b5158137cec9","def":"{\"v\":9,\"a\":[7,18,41],\"p\":[{\"b\":5,\"a\":[12],\"s\":[{\"p\":[0,0,0],\"r\":[0,0,0],\"s\":[2.853044,1.775563,0.1365793],\"c\":[1,1,1],\"b\":[\"when starts then set constant rotation to 0 550 0\",\"when touched then show areas \"]}]}]}"},{"id":"655e50b0baa2b214c006535f","def":"{\"v\":9,\"a\":[7,18,41],\"p\":[{\"b\":5,\"a\":[12],\"s\":[{\"p\":[0,0,0],\"r\":[0,0,0],\"s\":[2.815689,1.775563,0.1365793],\"c\":[1,1,1],\"b\":[\"when starts then set constant rotation to 0 150 0\",\"when touched then show areas \"]}]}]}"},{"id":"655e50b42ae71514cd3f0d9a","def":"{\"v\":9,\"a\":[7,18,41],\"p\":[{\"b\":5,\"a\":[12],\"s\":[{\"p\":[0,0,0],\"r\":[0,0,0],\"s\":[3.046599,1.775563,0.1365793],\"c\":[1,1,1],\"b\":[\"when starts then set constant rotation to 0 350 0\",\"when touched then show areas \"]}]}]}"},{"id":"655e50b9baa2b214c0065360","def":"{\"v\":9,\"a\":[7,18,41],\"p\":[{\"b\":5,\"a\":[12],\"s\":[{\"p\":[0,0,0],\"r\":[0,0,0],\"s\":[4.78645,1.775563,0.1442886],\"c\":[1,1,1],\"b\":[\"when starts then set constant rotation to 0 750 0\",\"when touched then show areas \"]}]}]}"},{"id":"655fa02ba5f43d14c216f5a8","def":"{\"v\":9,\"a\":[48,49],\"p\":[{\"a\":[12,36],\"s\":[{\"p\":[0,0,0],\"r\":[0,0,0],\"s\":[0.1750029,0.1750032,0.1750002],\"c\":[1,1,1],\"b\":[\"when starts then become untweened next in 45s\"]},{\"p\":[0,0,0],\"r\":[0,0,0],\"s\":[0.1750029,0.1750032,0.1750002],\"c\":[1,1,1],\"b\":[\"when starts then play heavy plasma shot with 500% , then become next in 0.1s\"]},{\"p\":[0,0,0],\"r\":[0,0,0],\"s\":[0.1750029,0.1750032,0.1750002],\"c\":[1,1,1],\"b\":[\"when starts then play heavy plasma shot with 500% , then become previous in 0.1s\"]}]}]}"}],"serveTime":32}