{"ok":true,"areaId":"5e2617e1a3a6473806f0c538","areaName":"depression mountain","areaKey":"rr5e2617e1f2cf753806312eed","areaCreatorId":"5c076575c75fcf650fdfb963","isPrivate":false,"isZeroGravity":false,"hasFloatingDust":false,"isCopyable":false,"onlyOwnerSetsLocks":false,"isExcluded":false,"environmentChangersJSON":"{\"environmentChangers\":[]}","requestorIsEditor":false,"requestorIsListEditor":false,"requestorIsOwner":false,"placements":[{"Id":"5e2617e1f2cf753806312eee","Tid":"000000000000000000000001","P":{"x":0.62715387344,"y":-0.275627732,"z":0.321439146995},"R":{"x":0,"y":0,"z":0}}],"serveTime":21}