{"ok":true,"areaId":"5e8230d4ad82176cfd3ed92d","areaName":"katrinagalvan0328's home","areaKey":"rr5e8230d4408c3d6cfd1572c0","areaCreatorId":"5e8230d4ad82176cfd3ed92c","isPrivate":false,"isZeroGravity":false,"hasFloatingDust":false,"isCopyable":false,"onlyOwnerSetsLocks":false,"isExcluded":false,"environmentChangersJSON":"{\"environmentChangers\":[]}","requestorIsEditor":false,"requestorIsListEditor":false,"requestorIsOwner":false,"placements":[{"Id":"5e8230d4408c3d6cfd1572c1","Tid":"000000000000000000000001","P":{"x":0.62715387344,"y":-0.275627732,"z":0.321439146995},"R":{"x":0,"y":0,"z":0}}],"serveTime":18}