{"ok":true,"areaId":"5c06e96775b22a64fb6e0551","areaName":"kimykimkim1000's home","areaKey":"rr5c06e9671df35964fb6eae7b","areaCreatorId":"5c06e96775b22a64fb6e0550","isPrivate":false,"isZeroGravity":false,"hasFloatingDust":false,"isCopyable":false,"onlyOwnerSetsLocks":false,"isExcluded":false,"environmentChangersJSON":"{\"environmentChangers\":[]}","requestorIsEditor":false,"requestorIsListEditor":false,"requestorIsOwner":false,"placements":[{"Id":"5c06e9671df35964fb6eae7c","Tid":"000000000000000000000001","P":{"x":0.62715387344,"y":-0.275627732,"z":0.321439146995},"R":{"x":0,"y":0,"z":0}}],"serveTime":20}