{"ok":true,"areaId":"5cb0b22821bdca26726f570c","areaName":"kiyaiwalid's home","areaKey":"rr5cb0b228643c8c26729869f7","areaCreatorId":"5cb0b22821bdca26726f570b","isPrivate":false,"isZeroGravity":false,"hasFloatingDust":false,"isCopyable":false,"onlyOwnerSetsLocks":false,"isExcluded":false,"environmentChangersJSON":"{\"environmentChangers\":[]}","requestorIsEditor":false,"requestorIsListEditor":false,"requestorIsOwner":false,"placements":[{"Id":"5cb0b228643c8c26729869f8","Tid":"000000000000000000000001","P":{"x":0.62715387344,"y":-0.275627732,"z":0.321439146995},"R":{"x":0,"y":0,"z":0}}],"serveTime":28}