{"ok":true,"areaId":"5c1bd2a983d725055c8f7c44","areaName":"noob's home","areaKey":"rr5c1bd2a9b38de5055cdc0f89","areaCreatorId":"5c1bd2a983d725055c8f7c43","isPrivate":false,"isZeroGravity":false,"hasFloatingDust":false,"isCopyable":false,"onlyOwnerSetsLocks":false,"isExcluded":false,"environmentChangersJSON":"{\"environmentChangers\":[]}","requestorIsEditor":false,"requestorIsListEditor":false,"requestorIsOwner":false,"placements":[{"Id":"5c1bd2a9b38de5055cdc0f8a","Tid":"000000000000000000000001","P":{"x":0.62715387344,"y":-0.275627732,"z":0.321439146995},"R":{"x":0,"y":0,"z":0}},{"Id":"5c1e44f176415126c091efc4","Tid":"5c1e44f183f66e6e5534004b","P":{"x":0.5192489624023438,"y":0.022218555212020874,"z":0.17246145009994507},"R":{"x":81.48373413085938,"y":227.02638244628906,"z":75.6570816040039},"S":1.0000004768371582}],"serveTime":12}