{"ok":true,"areaId":"6004e7eb28fa855aa12a1716","areaName":"nyah's home","areaKey":"rr6004e7eb24badd5aa1af8049","areaCreatorId":"6004e7eb28fa855aa12a1715","isPrivate":false,"isZeroGravity":false,"hasFloatingDust":false,"isCopyable":false,"onlyOwnerSetsLocks":false,"isExcluded":false,"environmentChangersJSON":"{\"environmentChangers\":[]}","requestorIsEditor":false,"requestorIsListEditor":false,"requestorIsOwner":false,"placements":[{"Id":"6004e7eb24badd5aa1af804a","Tid":"000000000000000000000001","P":{"x":0.62715387344,"y":-0.275627732,"z":0.321439146995},"R":{"x":0,"y":0,"z":0},"A":[1]}],"serveTime":23}