{"ok":true,"areaId":"5b6de24bc0f02674cb9188e6","areaName":"pikov18's home","areaKey":"rr5b6de24bed84a974cb4ec11f","areaCreatorId":"5b6de24bc0f02674cb9188e5","isPrivate":false,"isZeroGravity":false,"hasFloatingDust":false,"isCopyable":false,"onlyOwnerSetsLocks":false,"isExcluded":false,"environmentChangersJSON":"{\"environmentChangers\":[]}","requestorIsEditor":false,"requestorIsListEditor":false,"requestorIsOwner":false,"placements":[{"Id":"5b6de24bed84a974cb4ec120","Tid":"000000000000000000000001","P":{"x":0.62715387344,"y":-0.275627732,"z":0.321439146995},"R":{"x":0,"y":0,"z":0}}],"serveTime":21}