{"ok":true,"areaId":"5a19d5154c61d332109de6fa","areaName":"raoulos 's home","areaKey":"rr5a19d515fcfbf63210ed4a50","areaCreatorId":"5a19d5154c61d332109de6f9","isPrivate":false,"isZeroGravity":false,"hasFloatingDust":true,"isCopyable":false,"onlyOwnerSetsLocks":false,"isExcluded":false,"_environmentType":"Day","environmentChangersJSON":"{\"environmentChangers\":[{\"Name\":\"sun\",\"Rotation\":{\"x\":351.5553283691406,\"y\":323.82623291015625,\"z\":338.7632751464844},\"Scale\":0.05000004172325134,\"Color\":{\"r\":1,\"g\":1,\"b\":1,\"a\":1}},{\"Name\":\"night\",\"Rotation\":{\"x\":357.5591125488281,\"y\":14.875907897949219,\"z\":4.643550872802734},\"Scale\":0.05000001937150955,\"Color\":{\"r\":0.03999999910593033,\"g\":0.04999998211860657,\"b\":0.09999997168779373,\"a\":1}},{\"Name\":\"ambientLight\",\"Rotation\":{\"x\":3.677802562713623,\"y\":359.8827819824219,\"z\":1.9583040475845337},\"Scale\":0.10000000149011612,\"Color\":{\"r\":0.09999997168779373,\"g\":0.09899996966123581,\"b\":0.06999997794628143,\"a\":1}},{\"Name\":\"clouds\",\"Rotation\":{\"x\":355.4011535644531,\"y\":4.566786289215088,\"z\":2.52372670173645},\"Scale\":0.010000000707805157,\"Color\":{\"r\":1,\"g\":1,\"b\":1,\"a\":1}}]}","requestorIsEditor":false,"requestorIsListEditor":false,"requestorIsOwner":false,"placements":[{"Id":"5a19d515fcfbf63210ed4a51","Tid":"000000000000000000000001","P":{"x":0.62715387344,"y":-0.275627732,"z":0.321439146995},"R":{"x":0,"y":0,"z":0}}],"serveTime":15}