{"ok":true,"areaId":"5e1ffa74edc5ef4f51103d3a","areaName":"reeze the vampire's home","areaKey":"rr5e1ffa74a332fc4f51cff3ae","areaCreatorId":"5e1ffa74edc5ef4f51103d39","isPrivate":false,"isZeroGravity":false,"hasFloatingDust":false,"isCopyable":false,"onlyOwnerSetsLocks":false,"isExcluded":false,"environmentChangersJSON":"{\"environmentChangers\":[]}","requestorIsEditor":false,"requestorIsListEditor":false,"requestorIsOwner":false,"placements":[{"Id":"5e1ffa74a332fc4f51cff3af","Tid":"000000000000000000000001","P":{"x":0.62715387344,"y":-0.275627732,"z":0.321439146995},"R":{"x":0,"y":0,"z":0}}],"serveTime":32}