{"ok":true,"areaId":"5d4eda468040171b46aa73d3","areaName":"rockytza's home","areaKey":"rr5d4eda4645d6181b46b4d847","areaCreatorId":"5d4eda468040171b46aa73d2","isPrivate":false,"isZeroGravity":false,"hasFloatingDust":false,"isCopyable":false,"onlyOwnerSetsLocks":false,"isExcluded":false,"environmentChangersJSON":"{\"environmentChangers\":[]}","requestorIsEditor":false,"requestorIsListEditor":false,"requestorIsOwner":false,"placements":[{"Id":"5d4eda4645d6181b46b4d848","Tid":"000000000000000000000001","P":{"x":0.62715387344,"y":-0.275627732,"z":0.321439146995},"R":{"x":0,"y":0,"z":0}}],"serveTime":19}