{"ok":true,"areaId":"5a116cba457af53310e73dd4","areaName":"samvr's home","areaKey":"rr5a116cbad9be4d33109b4213","areaCreatorId":"5a116cba457af53310e73dd3","isPrivate":false,"isZeroGravity":false,"hasFloatingDust":false,"isCopyable":false,"onlyOwnerSetsLocks":false,"isExcluded":false,"_environmentType":"Day","environmentChangersJSON":"{\"environmentChangers\":[{\"Name\":\"night\",\"Rotation\":{\"x\":2.1703407764434814,\"y\":350.7170104980469,\"z\":3.1233999729156494},\"Scale\":0.05000000074505806,\"Color\":{\"r\":0.03999999910593033,\"g\":0.04999998211860657,\"b\":0.09999997168779373,\"a\":1}},{\"Name\":\"sun\",\"Rotation\":{\"x\":37.10464859008789,\"y\":108.02389526367188,\"z\":131.09201049804688},\"Scale\":0.04999998211860657,\"Color\":{\"r\":1,\"g\":1,\"b\":1,\"a\":1}}]}","requestorIsEditor":false,"requestorIsListEditor":false,"requestorIsOwner":false,"placements":[{"Id":"5a116cbad9be4d33109b4214","Tid":"000000000000000000000001","P":{"x":0.62715387344,"y":-0.275627732,"z":0.321439146995},"R":{"x":0,"y":0,"z":0}},{"Id":"5a116d6db795340b50ec1c77","Tid":"5a116d6f9c2ebcaa13a94178","P":{"x":0.6789716482162476,"y":0.0959259495139122,"z":0.5918005108833313},"R":{"x":0.000010017914064519573,"y":180,"z":270}}],"serveTime":21}