{"ok":true,"areaId":"5d292d8874304635373f2928","areaName":"ultra lemon's home","areaKey":"rr5d292d8833272c3537b62288","areaCreatorId":"5d292d8874304635373f2927","isPrivate":false,"isZeroGravity":false,"hasFloatingDust":false,"isCopyable":false,"onlyOwnerSetsLocks":false,"isExcluded":false,"environmentChangersJSON":"{\"environmentChangers\":[]}","requestorIsEditor":false,"requestorIsListEditor":false,"requestorIsOwner":false,"placements":[{"Id":"5d292d8833272c3537b62289","Tid":"000000000000000000000001","P":{"x":0.5912315845489502,"y":-0.3509911298751831,"z":-0.9308673143386841},"R":{"x":4.508508205413818,"y":61.77289962768555,"z":7.735919952392578},"S":86.69}],"serveTime":16}