{"ok":true,"areaId":"5c8f01344bb1e705520a36a8","areaName":"uy6789ok","areaKey":"rr5c8f01343c07b20552b7d1d8","areaCreatorId":"5c8eff363d38444bdac843cc","isPrivate":false,"isZeroGravity":false,"hasFloatingDust":false,"isCopyable":false,"onlyOwnerSetsLocks":false,"isExcluded":false,"environmentChangersJSON":"{\"environmentChangers\":[]}","requestorIsEditor":false,"requestorIsListEditor":false,"requestorIsOwner":false,"placements":[{"Id":"5c8f01343c07b20552b7d1d9","Tid":"000000000000000000000001","P":{"x":0.62715387344,"y":-0.275627732,"z":0.321439146995},"R":{"x":0,"y":0,"z":0}}],"serveTime":12}