{"ok":true,"areaId":"5aa6f6f0c5eda013d8e57d48","areaName":"whatwouldyoudoforaklondikebar's home","areaKey":"rr5aa6f6f00029cf13d886c1f2","areaCreatorId":"5aa6f6f0c5eda013d8e57d47","isPrivate":false,"isZeroGravity":false,"hasFloatingDust":false,"isCopyable":false,"onlyOwnerSetsLocks":false,"isExcluded":false,"environmentChangersJSON":"{\"environmentChangers\":[]}","requestorIsEditor":false,"requestorIsListEditor":false,"requestorIsOwner":false,"placements":[{"Id":"5aa6f6f00029cf13d886c1f3","Tid":"000000000000000000000001","P":{"x":0.62715387344,"y":-0.275627732,"z":0.321439146995},"R":{"x":0,"y":0,"z":0}},{"Id":"5aa6f745c26b3f0a74e6a38e","Tid":"5aa6f74712aa0a05f9b239a4","P":{"x":0.10844846069812775,"y":0.931408166885376,"z":-0.2772722542285919},"R":{"x":330.19091796875,"y":107.39613342285156,"z":42.264617919921875}}],"serveTime":23}