{"ok":true,"areaId":"5c743cea4219b542c363c069","areaName":"augusto da meiota's home","areaKey":"rr5c743cea6eaf4942c384a338","areaCreatorId":"5c743cea4219b542c363c068","isPrivate":false,"isZeroGravity":false,"hasFloatingDust":false,"isCopyable":false,"onlyOwnerSetsLocks":false,"isExcluded":false,"environmentChangersJSON":"{\"environmentChangers\":[]}","requestorIsEditor":false,"requestorIsListEditor":false,"requestorIsOwner":false,"placements":[{"Id":"5c743cea6eaf4942c384a339","Tid":"000000000000000000000001","P":{"x":0.62715387344,"y":-0.275627732,"z":0.321439146995},"R":{"x":0,"y":0,"z":0}}],"serveTime":14}