{"ok":true,"areaId":"6066e3cfc54299054eff156b","areaName":"bebo's home","areaKey":"rr6066e3cf8f4a7b054e13f9de","areaCreatorId":"6066e3cfc54299054eff156a","isPrivate":false,"isZeroGravity":false,"hasFloatingDust":false,"isCopyable":false,"onlyOwnerSetsLocks":false,"isExcluded":false,"environmentChangersJSON":"{\"environmentChangers\":[]}","requestorIsEditor":false,"requestorIsListEditor":false,"requestorIsOwner":false,"placements":[{"Id":"6066e3cf8f4a7b054e13f9df","Tid":"000000000000000000000001","P":{"x":0.62715387344,"y":-0.275627732,"z":0.321439146995},"R":{"x":0,"y":0,"z":0},"A":[1]}],"serveTime":17}