{"ok":true,"areaId":"5da7dfb065ad7e062e08fb2d","areaName":"bgoodwin38606's home","areaKey":"rr5da7dfb099d345062ecd2204","areaCreatorId":"5da7dfb065ad7e062e08fb2c","isPrivate":false,"isZeroGravity":false,"hasFloatingDust":false,"isCopyable":false,"onlyOwnerSetsLocks":false,"isExcluded":false,"environmentChangersJSON":"{\"environmentChangers\":[]}","requestorIsEditor":false,"requestorIsListEditor":false,"requestorIsOwner":false,"placements":[{"Id":"5da7dfb099d345062ecd2205","Tid":"5da7e01be0160406287922e2","P":{"x":1.1468846797943115,"y":-0.7642129063606262,"z":0.20452606678009033},"R":{"x":7.256330966949463,"y":5.789929389953613,"z":12.942042350769043}}],"serveTime":21}