{"ok":true,"areaId":"607bd47b10343c308c387888","areaName":"dakkua's home","areaKey":"rr607bd47bd197a5308c686a65","areaCreatorId":"607bd47b10343c308c387887","isPrivate":false,"isZeroGravity":false,"hasFloatingDust":false,"isCopyable":false,"onlyOwnerSetsLocks":false,"isExcluded":false,"environmentChangersJSON":"{\"environmentChangers\":[]}","requestorIsEditor":false,"requestorIsListEditor":false,"requestorIsOwner":false,"placements":[{"Id":"607bd47bd197a5308c686a66","Tid":"000000000000000000000001","P":{"x":0.62715387344,"y":-0.275627732,"z":0.321439146995},"R":{"x":0,"y":0,"z":0},"A":[1]},{"Id":"607bd4d41791e43ea8517999","Tid":"607bd4d5b9d3fc0557cc36c5","P":{"x":-0.014964461326599121,"y":1.32561194896698,"z":-0.46115198731422424},"R":{"x":330.3389587402344,"y":114.76709747314453,"z":265.5098571777344},"S":0.9999998807907104}],"serveTime":18}