{"ok":true,"areaId":"5d2504ddc268bc353120d064","areaName":"deadshot gaming's home","areaKey":"rr5d2504dd2edcf23531538f60","areaCreatorId":"5d2504ddc268bc353120d063","isPrivate":false,"isZeroGravity":false,"hasFloatingDust":false,"isCopyable":false,"onlyOwnerSetsLocks":false,"isExcluded":false,"environmentChangersJSON":"{\"environmentChangers\":[]}","requestorIsEditor":false,"requestorIsListEditor":false,"requestorIsOwner":false,"placements":[{"Id":"5d2504dd2edcf23531538f61","Tid":"000000000000000000000001","P":{"x":0.62715387344,"y":-0.275627732,"z":0.321439146995},"R":{"x":0,"y":0,"z":0}}],"serveTime":16}