{"ok":true,"areaId":"5cb37fd7981488266be4bae7","areaName":"death stalker's home","areaKey":"rr5cb37fd707549b266b5d061d","areaCreatorId":"5cb37fd7981488266be4bae6","isPrivate":false,"isZeroGravity":false,"hasFloatingDust":false,"isCopyable":false,"onlyOwnerSetsLocks":false,"isExcluded":false,"environmentChangersJSON":"{\"environmentChangers\":[]}","requestorIsEditor":false,"requestorIsListEditor":false,"requestorIsOwner":false,"placements":[{"Id":"5cb37fd707549b266b5d061e","Tid":"5cb380399d69377040903f01","P":{"x":0.6271538734436035,"y":-0.2756277322769165,"z":0.32143914699554443},"R":{"x":0,"y":0,"z":0}}],"serveTime":26}