{"ok":true,"areaId":"59daef44736c05b11306e525","areaName":"domino home","areaKey":"rr59daef446de495b113c1dd2b","areaCreatorId":"59bb15543b4051a813794f66","isPrivate":false,"isZeroGravity":false,"hasFloatingDust":false,"isCopyable":false,"onlyOwnerSetsLocks":false,"isExcluded":false,"_environmentType":"City4","environmentChangersJSON":"{\"environmentChangers\":[{\"Name\":\"sun\",\"Rotation\":{\"x\":319.35552978515625,\"y\":186.98141479492188,\"z\":291.1689453125},\"Scale\":0.05000020191073418,\"Color\":{\"r\":1,\"g\":1,\"b\":1,\"a\":1}}]}","requestorIsEditor":false,"requestorIsListEditor":false,"requestorIsOwner":false,"placements":[],"serveTime":21}