{"ok":true,"areaId":"5bcd0478dacbac65d887cbce","areaName":"eatenaliveavi","areaKey":"rr5bcd04788a8fa965d8c8cd9b","areaCreatorId":"5a348c4f2047d49b13d86aca","isPrivate":false,"isZeroGravity":false,"hasFloatingDust":false,"isCopyable":false,"onlyOwnerSetsLocks":false,"isExcluded":false,"environmentChangersJSON":"{\"environmentChangers\":[]}","requestorIsEditor":false,"requestorIsListEditor":false,"requestorIsOwner":false,"placements":[{"Id":"5bcd04788a8fa965d8c8cd9c","Tid":"000000000000000000000001","P":{"x":0.62715387344,"y":-0.275627732,"z":0.321439146995},"R":{"x":0,"y":0,"z":0}},{"Id":"5bcd04e240f6460ac09dce85","Tid":"5bcd04e13867360572974bb5","P":{"x":0.48900434374809265,"y":1.7158774137496948,"z":0.9655921459197998},"R":{"x":3.249993324279785,"y":24.89263916015625,"z":359.6524353027344}}],"serveTime":13}