{"ok":true,"areaId":"5b7c1c9aa26b660e8e21b1e8","areaName":"florian59930's home","areaKey":"rr5b7c1c9a0cbd8d0e8e307b45","areaCreatorId":"5b7c1c9aa26b660e8e21b1e7","isPrivate":false,"isZeroGravity":false,"hasFloatingDust":false,"isCopyable":false,"onlyOwnerSetsLocks":false,"isExcluded":false,"environmentChangersJSON":"{\"environmentChangers\":[]}","requestorIsEditor":false,"requestorIsListEditor":false,"requestorIsOwner":false,"placements":[{"Id":"5b7c1c9a0cbd8d0e8e307b46","Tid":"000000000000000000000001","P":{"x":0.62715387344,"y":-0.275627732,"z":0.321439146995},"R":{"x":0,"y":0,"z":0}}],"serveTime":11}