{"ok":true,"areaId":"5f2e46b411766f3186f93a25","areaName":"home 3150","areaKey":"rr5f2e46b4f0ff3531868c1ff8","areaCreatorId":"5f2e46b411766f3186f93a24","isPrivate":false,"isZeroGravity":false,"hasFloatingDust":false,"isCopyable":false,"onlyOwnerSetsLocks":false,"isExcluded":false,"environmentChangersJSON":"{\"environmentChangers\":[]}","requestorIsEditor":false,"requestorIsListEditor":false,"requestorIsOwner":false,"placements":[{"Id":"5f2e46b4f0ff3531868c1ff9","Tid":"000000000000000000000001","P":{"x":0.6271538734436035,"y":-0.2756277322769165,"z":0.32143914699554443},"R":{"x":0,"y":0,"z":0},"A":[]}],"serveTime":310}