{"ok":true,"areaId":"5bb8de0d5b53e54526129a04","areaName":"home 2459","areaKey":"rr5bb8de0decde4f452680815c","areaCreatorId":"5bb8de0d5b53e54526129a03","isPrivate":false,"isZeroGravity":false,"hasFloatingDust":false,"isCopyable":false,"onlyOwnerSetsLocks":false,"isExcluded":false,"environmentChangersJSON":"{\"environmentChangers\":[]}","requestorIsEditor":false,"requestorIsListEditor":false,"requestorIsOwner":false,"placements":[{"Id":"5bb8de0decde4f452680815d","Tid":"000000000000000000000001","P":{"x":0.62715387344,"y":-0.275627732,"z":0.321439146995},"R":{"x":0,"y":0,"z":0}}],"serveTime":219}