{"ok":true,"areaId":"5d6beee2309ea4392c5a7403","areaName":"home 2928","areaKey":"rr5d6beee25cca68392c33ae40","areaCreatorId":"5d6beee2309ea4392c5a7402","isPrivate":false,"isZeroGravity":false,"hasFloatingDust":false,"isCopyable":false,"onlyOwnerSetsLocks":false,"isExcluded":false,"environmentChangersJSON":"{\"environmentChangers\":[]}","requestorIsEditor":false,"requestorIsListEditor":false,"requestorIsOwner":false,"placements":[{"Id":"5d6beee25cca68392c33ae41","Tid":"000000000000000000000001","P":{"x":0.2619076371192932,"y":-0.9732167720794678,"z":0.1585007905960083},"R":{"x":357.3882751464844,"y":7.603229999542236,"z":356.2434997558594}}],"serveTime":325}