{"ok":true,"areaId":"5bc324439faa443253411a44","areaName":"hool door's home","areaKey":"rr5bc32443b43d733253321e5c","areaCreatorId":"5bc324439faa443253411a43","isPrivate":false,"isZeroGravity":false,"hasFloatingDust":false,"isCopyable":false,"onlyOwnerSetsLocks":false,"isExcluded":false,"environmentChangersJSON":"{\"environmentChangers\":[]}","requestorIsEditor":false,"requestorIsListEditor":false,"requestorIsOwner":false,"placements":[{"Id":"5bc32443b43d733253321e5d","Tid":"000000000000000000000001","P":{"x":0.62715387344,"y":-0.275627732,"z":0.321439146995},"R":{"x":0,"y":0,"z":0}}],"serveTime":54}