{"ok":true,"areaId":"5cd9c1fc1574305d9ef980fb","areaName":"hvneren's home","areaKey":"rr5cd9c1fcae0a795d9ec8ef68","areaCreatorId":"5cd9c1fc1574305d9ef980fa","isPrivate":false,"isZeroGravity":false,"hasFloatingDust":false,"isCopyable":false,"onlyOwnerSetsLocks":false,"isExcluded":false,"environmentChangersJSON":"{\"environmentChangers\":[]}","requestorIsEditor":false,"requestorIsListEditor":false,"requestorIsOwner":false,"placements":[{"Id":"5cd9c1fcae0a795d9ec8ef69","Tid":"000000000000000000000001","P":{"x":0.6555154323577881,"y":-0.26811152696609497,"z":0.3492967486381531},"R":{"x":6.407764434814453,"y":357.26739501953125,"z":359.81854248046875},"S":1.9377}],"serveTime":19}