{"ok":true,"areaId":"5c72400426ec1d0e7c6bf1dc","areaName":"jett not jeff's home","areaKey":"rr5c7240040bd50f0e7c7138ca","areaCreatorId":"5c72400326ec1d0e7c6bf1db","isPrivate":false,"isZeroGravity":false,"hasFloatingDust":false,"isCopyable":false,"onlyOwnerSetsLocks":false,"isExcluded":false,"environmentChangersJSON":"{\"environmentChangers\":[]}","requestorIsEditor":false,"requestorIsListEditor":false,"requestorIsOwner":false,"placements":[{"Id":"5c7240040bd50f0e7c7138cb","Tid":"000000000000000000000001","P":{"x":0.62715387344,"y":-0.275627732,"z":0.321439146995},"R":{"x":0,"y":0,"z":0}},{"Id":"5c72405f1705642818d76a5c","Tid":"5c72405e3543572aae46023d","P":{"x":0.021267276257276535,"y":0.6390134692192078,"z":0.38213545083999634},"R":{"x":0.3994719684123993,"y":52.386165618896484,"z":272.58380126953125}}],"serveTime":27}