{"ok":true,"areaId":"5bcd96075d9de633b45ff2f1","areaName":"mooshymoo's home","areaKey":"rr5bcd9607394fbb33b4545739","areaCreatorId":"5bcd96075d9de633b45ff2f0","isPrivate":false,"isZeroGravity":false,"hasFloatingDust":false,"isCopyable":false,"onlyOwnerSetsLocks":false,"isExcluded":false,"environmentChangersJSON":"{\"environmentChangers\":[]}","requestorIsEditor":false,"requestorIsListEditor":false,"requestorIsOwner":false,"placements":[{"Id":"5bcd9607394fbb33b454573a","Tid":"000000000000000000000001","P":{"x":0.62715387344,"y":-0.275627732,"z":0.321439146995},"R":{"x":0,"y":0,"z":0}}],"serveTime":29}