{"ok":true,"areaId":"5bf629b888c030056a69cbdd","areaName":"philipp","areaKey":"rr5bf629b81cd915056ad859ca","areaCreatorId":"586803270156365c24f9be9d","isPrivate":false,"isZeroGravity":false,"hasFloatingDust":false,"isCopyable":false,"onlyOwnerSetsLocks":false,"isExcluded":false,"environmentChangersJSON":"{\"environmentChangers\":[{\"Name\":\"sun\",\"Rotation\":{\"x\":329.39501953125,\"y\":309.3611755371094,\"z\":216.5479278564453},\"Scale\":0.04999984800815582,\"Color\":{\"r\":1,\"g\":1,\"b\":1,\"a\":1}}]}","requestorIsEditor":false,"requestorIsListEditor":false,"requestorIsOwner":false,"placements":[{"Id":"5bf629b81cd915056ad859cb","Tid":"5bf629cf1171b264597366ed","P":{"x":0.6271538734436035,"y":-0.2756277322769165,"z":0.32143914699554443},"R":{"x":0,"y":0,"z":0}}],"serveTime":14}