{"ok":true,"areaId":"5a21dfb55b598a2410e37973","areaName":"reaper7753's home","areaKey":"rr5a21dfb5e70dfa24103e2ab7","areaCreatorId":"5a21dfb55b598a2410e37972","isPrivate":false,"isZeroGravity":false,"hasFloatingDust":false,"isCopyable":false,"onlyOwnerSetsLocks":false,"isExcluded":false,"_environmentType":"Day","environmentChangersJSON":"{\"environmentChangers\":[{\"Name\":\"sun\",\"Rotation\":{\"x\":316.45538330078125,\"y\":224.4360809326172,\"z\":274.41949462890625},\"Scale\":0.044615812599658966,\"Color\":{\"r\":1,\"g\":1,\"b\":1,\"a\":1}}]}","requestorIsEditor":false,"requestorIsListEditor":false,"requestorIsOwner":false,"placements":[{"Id":"5a21dfb5e70dfa24103e2ab8","Tid":"000000000000000000000001","P":{"x":0.62715387344,"y":-0.275627732,"z":0.321439146995},"R":{"x":0,"y":0,"z":0}}],"serveTime":29}