{"ok":true,"areaId":"5a9a2d5381a5bcad133b4b81","areaName":"revolving door ocelot's home","areaKey":"rr5a9a2d53dc2030ad137e10f0","areaCreatorId":"5a9a2d5381a5bcad133b4b80","isPrivate":false,"isZeroGravity":false,"hasFloatingDust":false,"isCopyable":false,"onlyOwnerSetsLocks":false,"isExcluded":false,"environmentChangersJSON":"{\"environmentChangers\":[]}","requestorIsEditor":false,"requestorIsListEditor":false,"requestorIsOwner":false,"placements":[{"Id":"5a9a2d53dc2030ad137e10f1","Tid":"000000000000000000000001","P":{"x":0.62715387344,"y":-0.275627732,"z":0.321439146995},"R":{"x":0,"y":0,"z":0}}],"serveTime":24}