{"ok":true,"areaId":"5ba26e4de20e0462ce2ccf37","areaName":"sebastian-a-m's home","areaKey":"rr5ba26e4d45d9f762ce6591f3","areaCreatorId":"5ba26e4de20e0462ce2ccf36","isPrivate":false,"isZeroGravity":false,"hasFloatingDust":false,"isCopyable":false,"onlyOwnerSetsLocks":false,"isExcluded":false,"environmentChangersJSON":"{\"environmentChangers\":[]}","requestorIsEditor":false,"requestorIsListEditor":false,"requestorIsOwner":false,"placements":[{"Id":"5ba26e4d45d9f762ce6591f4","Tid":"000000000000000000000001","P":{"x":0.62715387344,"y":-0.275627732,"z":0.321439146995},"R":{"x":0,"y":0,"z":0}}],"serveTime":18}