{"ok":true,"areaId":"5a55223c4b48966d145b7225","areaName":"simonanero191's home","areaKey":"rr5a55223cf454a06d14f54089","areaCreatorId":"5a55223c4b48966d145b7224","isPrivate":false,"isZeroGravity":false,"hasFloatingDust":false,"isCopyable":false,"onlyOwnerSetsLocks":false,"isExcluded":false,"environmentChangersJSON":"{\"environmentChangers\":[]}","requestorIsEditor":false,"requestorIsListEditor":false,"requestorIsOwner":false,"placements":[{"Id":"5a55223cf454a06d14f5408a","Tid":"000000000000000000000001","P":{"x":0.62715387344,"y":-0.275627732,"z":0.321439146995},"R":{"x":0,"y":0,"z":0}}],"serveTime":17}