{"ok":true,"areaId":"5ac2a8b95b18020fead22033","areaName":"sir leinad's home","areaKey":"rr5ac2a8b922cf890feac8c1e9","areaCreatorId":"5ac2a8b95b18020fead22032","isPrivate":false,"isZeroGravity":false,"hasFloatingDust":false,"isCopyable":false,"onlyOwnerSetsLocks":false,"isExcluded":false,"environmentChangersJSON":"{\"environmentChangers\":[]}","requestorIsEditor":false,"requestorIsListEditor":false,"requestorIsOwner":false,"placements":[{"Id":"5ac2a8b922cf890feac8c1ea","Tid":"000000000000000000000001","P":{"x":0.62715387344,"y":-0.275627732,"z":0.321439146995},"R":{"x":0,"y":0,"z":0}},{"Id":"5ac2a8e9e9bdb71534b79927","Tid":"5ac2a8e96cf50a13eed64802","P":{"x":1.7189445495605469,"y":0.9250127673149109,"z":2.1180903911590576},"R":{"x":357.059814453125,"y":80.37615966796875,"z":299.9501037597656},"S":1.000000238418579}],"serveTime":21}