{"ok":true,"areaId":"5a809968149edb7e13c13059","areaName":"vathugu's home","areaKey":"rr5a8099682a0b5f7e130de0c8","areaCreatorId":"5a809968149edb7e13c13058","isPrivate":false,"isZeroGravity":false,"hasFloatingDust":false,"isCopyable":false,"onlyOwnerSetsLocks":false,"isExcluded":false,"_environmentType":"Snow","environmentChangersJSON":"{\"environmentChangers\":[]}","requestorIsEditor":false,"requestorIsListEditor":false,"requestorIsOwner":false,"placements":[{"Id":"5a8099682a0b5f7e130de0c9","Tid":"000000000000000000000001","P":{"x":0.62715387344,"y":-0.275627732,"z":0.321439146995},"R":{"x":0,"y":0,"z":0}},{"Id":"5a809bff06f6aa534097c7c0","Tid":"5a809c0100ff22e90fc7ff31","P":{"x":0.19057045876979828,"y":1.1002413034439087,"z":0.6421523690223694},"R":{"x":4.978978157043457,"y":318.9706115722656,"z":357.35809326171875}}],"serveTime":26}