{"ok":true,"areaId":"5e2f0a0ba35bc84f574c18bf","areaName":"zentrifuge's home","areaKey":"rr5e2f0a0b5589814f574bccc2","areaCreatorId":"5e2f0a0ba35bc84f574c18be","isPrivate":false,"isZeroGravity":false,"hasFloatingDust":false,"isCopyable":false,"onlyOwnerSetsLocks":false,"isExcluded":false,"environmentChangersJSON":"{\"environmentChangers\":[]}","requestorIsEditor":false,"requestorIsListEditor":false,"requestorIsOwner":false,"placements":[{"Id":"5e2f0a0b5589814f574bccc3","Tid":"000000000000000000000001","P":{"x":0.62715387344,"y":-0.275627732,"z":0.321439146995},"R":{"x":0,"y":0,"z":0}}],"serveTime":10}