{"areas":[{"name":"halloween town","id":"57f9c4edbf3d8ea711ce97ff","playerCount":0},{"name":"the friendship","id":"57f9e8360ed32f9e2755372e","playerCount":0},{"name":"the ruines","id":"586ca7d7eff6482710b5de25","playerCount":0},{"name":"the labyrinth","id":"5806cd78520f86df0fd8b6ad","playerCount":0},{"name":"oddworld","id":"57f8af68fc49639313af0dbe","playerCount":0},{"name":"the woods","id":"59261eac2013179d2a35ef69","playerCount":0},{"name":"the elf shelf","id":"57f9e8fa68d715a710634f7f","playerCount":0}],"ownPrivateAreas":[]}