{"editors":[{"id":"5c68f540636c692876543bb3","name":"soda","isOwner":true},{"id":"5a1f4bf2de5ff9b61360fc10","name":"dr.tangerine"},{"id":"5b7b28e2e06df428ae824917","name":"keys"},{"id":"5b773104031d397ea66e1ace","name":"lenzic"},{"id":"5bb6693c236557585f156458","name":"rustybot"},{"id":"5cbcd17cfb0ce7267153a4f2","name":"crimsontaylor"},{"id":"5c859df466b4c9393d81057c","name":"soup"},{"id":"5c71f188e59c5e5b788bbeba","name":"cjramos22"},{"id":"58413d84bb0909927d65f161","name":"styx"}],"listEditors":[{"id":"5c859df466b4c9393d81057c","name":"soup"}],"copiedFromAreas":[],"name":"soda's spaceship","creationDate":"2019-04-13T02:05:37.080Z","totalVisitors":316,"isZeroGravity":false,"hasFloatingDust":false,"isCopyable":false,"onlyOwnerSetsLocks":true,"isExcluded":false,"renameCount":0,"copiedCount":0,"isFavorited":false}