{"n":"thing","a":[2,7,18],"p":[{"b":5,"t":7,"s":[{"p":[0,0,0],"r":[0,0,0],"s":[0.01938329,0.01938395,0.08251223],"c":[0.3333329,0.3333329,0.3333329],"b":["when taken then become 2 in 0s"]},{"p":[0,0,0],"r":[0,0,0],"s":[0.01938329,0.01938395,0.08251223],"c":[0.3333333,0.3333333,0.3333333],"b":["when hit then become 3 in 0s","when touches liquor then tell fill"]},{"p":[0,0,0],"r":[0,0,0],"s":[0.01938329,0.01938395,0.08251223],"c":[0.3333333,0.3333333,0.3333333],"b":["when starts then destroy all parts","when starts then play glass bottle smashing","when starts then add crumbles for all parts"]}]},{"b":5,"t":7,"s":[{"p":[0,3.72529E-09,-0.02687741],"r":[0,0,0],"s":[0.01773251,0.01865346,0.005000235],"c":[0,0,0],"b":["when touches liquor then become 2 in 0.5s","when told fill then become 2 in 0.5s"]},{"p":[0,-1.164153E-10,0.000834942],"r":[0,0,0],"s":[0.01773283,0.0186568,0.08120701],"c":[0.3333333,0.05714277,0],"b":["when consumed then become 3 in 0.5s","when consumed then play slurping drink gulp"]},{"p":[0,3.72529E-09,-0.02862692],"r":[0,0,-1.001791E-05],"s":[0.01773282,0.01865801,0.005000229],"c":[0.3333331,0.05714263,0],"b":["when starts then become 1 in 0.5s"]}]}]}