{"n":"thing","p":[{"t":8,"a":[12],"s":[{"p":[0,0,0],"r":[0,0,0],"s":[0.06458868,0.06747559,0.08716924],"c":[1,1,1],"b":["when starts then play eerie space","when starts then become next in 3s"]},{"p":[0,0,0],"r":[0,0,0],"s":[0.06458868,0.06747559,0.08716924],"c":[1,1,1],"b":["when starts then play futuristic warp","when starts then become next in 4s"]},{"p":[0,0,0],"r":[0,0,0],"s":[0.06458868,0.06747559,0.08716924],"c":[1,1,1],"b":["when starts then play futuristic warp","when starts then become next in 4s"]}]}]}