{"n":"thing","v":3,"p":[{"b":131,"e":"Yes","s":[{"p":[0.07256911,-0.1829413,-0.02643888],"r":[40.45884,352.6207,349.8018],"s":[0.001000002,0.0009999997,0.001000001],"c":[0,0,0],"b":["when told by any greeting1 then become next in 1s"]},{"p":[0.08166215,-0.1850906,-0.02571257],"r":[33.40766,354.5755,352.7669],"s":[0.001000002,0.001,0.001000001],"c":[0,0,0],"b":["when starts then become next","when starts then tell any 1yes"]},{"p":[0,0,0],"r":[0,0,1.000516E-07],"s":[0.003,0.003000001,0.003000001],"c":[0,0,0],"b":["when told by any no1 then become next","when told by any yes1 then become next"]}]}]}