{"n":"mandrino","v":4,"a":[2,22,12,13,14,18,45,48,49],"inc":[["thing","5b0f334e4178730f9bf36ecd"],["thing 2","5b0f4ca802d9bb1eb7a2c8a4"],["thing 3","5b11ae3819c9df1ec8193366"],["thing 4","5b11af6b3f3a8c3bc333d7f2"]],"tp_d": 3,"tp_d": 3,"tp_lp": [1,0,0],"tp_d": 3,"tp_d": 3,"tp_lp": [1,0,0],"tp_lr": [1,1,1],"p":[{"a":[37],"s":[{"p":[-2.014858E-06,0.01850453,0.006816326],"r":[-2.067735E-07,180,180],"s":[0.00570407,0.0057043,0.005704486],"c":[1,1,1],"b":["when told jump then become next"]},{"p":[-2.014858E-06,0.01850453,0.006816326],"r":[-2.067735E-07,180,180],"s":[0.00570407,0.0057043,0.005704486],"c":[1,1,1],"b":["when starts then tell jump","when starts then become previous"]}]},{"a":[37],"s":[{"p":[-7.275376E-07,-0.01865108,0.006816456],"r":[-2.067735E-07,180,180],"s":[0.005704243,0.005704832,0.005704695],"c":[1,1,1],"b":["when told grounded then tell any grounded","when told jump then play coin with very-low-pitch ","when told by any shell then tell shell"]},{"p":[-7.275376E-07,-0.01865108,0.006816456],"r":[-2.067735E-07,180,180],"s":[0.005704243,0.005704832,0.005704695],"c":[1,1,1],"b":["when starts then become previous"]}]},{"a":[37,36],"s":[{"p":[-0.001218398,-0.01875663,0.02075242],"r":[3.521816E-06,180,180],"s":[0.005704295,0.00570491,0.005704807],"c":[1,1,1],"b":["when told by any shell then tell shell, then become next","when told by any shellr then tell shellr, then become 3"]},{"p":[-0.001218398,-0.01875663,0.02075242],"r":[3.521816E-06,180,180],"s":[0.005704295,0.00570491,0.005704807],"c":[1,1,1],"b":["when told action then tell noshell, then become previous"]},{"p":[-0.001218398,-0.01875663,0.02075242],"r":[3.521816E-06,180,180],"s":[0.005704295,0.00570491,0.005704807],"c":[1,1,1],"b":["when told action then tell noshellr, then become 1"]}]},{"a":[38],"s":[{"p":[-0.001113892,0.001614578,0.05169011],"r":[90,-1.001791E-05,0],"s":[0.01570194,0.005000949,0.01644232],"c":[1,1,1],"b":["when told by any right then propel forward with 1.5, then tell run, then tell right, then add speed 0 0 -.02","when told by any jump then tell jump, then call me kill","when told by any left then propel forward with -1.5, then tell run, then tell left, then add speed 0 0 .02","when told by any rightsprint then propel forward with 1.8, then tell run, then tell right, then add speed 0 0 -.04","when told by any leftsprint then propel forward with -1.8, then tell run, then tell left, then add speed 0 0 0.04","when told by any done then propel forward with 0, then tell done","when told by any jdone then tell jdone","when any part touches 1 then destroy all parts, then tell dead","when touches bump then set speed 0 0.3 0","when touches bump then tell grounded, then tell any grounded","when touches ground then tell grounded, then call me kick","when touches bump then call me kill","when any part touches deathshell then tell dead, then destroy all parts","when told by any a1 then tell action","when told by any grow then destroy all parts"]},{"p":[-0.002554776,0.0002299137,0.05169014],"r":[88.29108,177.6499,182.3487],"s":[0.01570167,0.005000489,0.01373664],"c":[1,1,1],"b":["when starts then become previous"]}]},{"a":[37],"i":[{"t":"5b11e3f4fde3ec03d83a10bc","p":[-0.01941457,0.0002924521,0.02525321],"r":[355.0723,271.7145,265.1528],"a":[48]},{"t":"5b11e4c82486eb3bb693be45","p":[-0.001763886,-0.0007288845,0.01781182],"r":[355.1707,181.2971,184.9453]}],"s":[{"p":[0.0001068115,0.001848222,0.004679233],"r":[1.708184,355.3001,94.92994],"s":[0.005707345,0.00570661,0.005706921],"c":[1,1,1],"b":["when told jump then add speed 0 .4 0","when starts then propel forward with 1","when told left then become 2","when told jdone then add speed 0 -0.15 0","when told jump then propel forward with 2","when told grounded then propel forward with 1"]},{"p":[0.0001068116,0.001848221,0.002276063],"r":[6.037092E-07,6.037091E-07,270],"s":[0.005709301,0.005709165,0.005709396],"c":[1,1,1],"b":["when told jump then add speed 0 .3 0","when told right then become 1","when starts then propel forward with 1","when told jdone then add speed 0 -0.15 0","when starts then turn sub-thing uncollidable"]}]},{"a":[38],"s":[{"p":[0,0.001944544,0.01784587],"r":[0,180,180],"s":[0.005704332,0.01095269,0.005705055],"c":[1,1,1],"b":["when touches mystery then tell first of any hit, then become next ","when touches brick then tell first of any hbump, then become next "]},{"p":[0,0.001944544,0.01784587],"r":[0,180,180],"s":[0.005704332,0.01095269,0.005705055],"c":[1,1,1],"b":["when starts then become previous in 0.4s"]}]},{"a":[37,14],"s":[{"p":[0.005828857,0.001984589,-0.06891287],"r":[-6.037092E-07,6.037092E-07,90],"s":[0.005706936,0.005708648,0.005709315],"c":[1,1,1],"b":["when told dead then emit gravity-free thing 2 with -10","when told by any grow then become 2","when told dead then play funny cute sound 7"]},{"p":[0.0002975465,0.001984594,-0.01344109],"r":[-6.037092E-07,6.037092E-07,90],"s":[0.00570754,0.005709224,0.005709927],"c":[1,1,1]}]}]}