{"n":"copper rock","v":9,"a":[31],"inc":[["stone","5ca971b60d820c7d8a9ad43b"],["ironore","5ca97ae8eb795e2f9768a911"],["gold ore","5ca9c85c6040515b6de8f99f"],["copper","5ca9c0370002a5480fc04481"]],"p":[{"b":158,"t1":43,"s":[{"p":[0,0,0],"r":[0,0,0],"s":[0.5012112,0.5011793,0.5012084],"c":[0.6666667,0.6666667,0.6666667],"b":["when is hp <= 0 then emit stone with 0"],"t1":{"c":[0,0,0],"x":0.5,"y":0.5,"a":0.8925,"m":0,"n":0,"r":0,"g":0,"o":0.5,"t":0.5,"e":0.5}}]},{"b":158,"t1":43,"s":[{"p":[0.1013415,0.1867026,-0.7333857],"r":[0,0,0],"s":[0.6161383,0.6160444,0.6161392],"c":[0.6666667,0.6666667,0.6666667],"b":["when is hp <= 0 then emit stone with 0"],"t1":{"c":[0,0,0],"x":0.5,"y":0.5,"a":0.8925,"m":0,"n":0,"r":0,"g":0,"o":0.5,"t":0.5,"e":0.5}}]},{"b":158,"t1":43,"s":[{"p":[0.5957843,0.218849,-0.2675349],"r":[-1.001792E-05,270,1.001791E-05],"s":[0.6538458,1.032474,0.6538467],"c":[0.6666667,0.6666667,0.6666667],"b":["when is hp <= 0 then emit stone with 0"],"t1":{"c":[0,0,0],"x":0.5,"y":0.5,"a":0.8925,"m":0,"n":0,"r":0,"g":0,"o":0.5,"t":0.5,"e":0.5}}]},{"b":158,"t1":43,"s":[{"p":[0.3180401,0.9447953,-0.3486884],"r":[-1.001792E-05,270,1.001791E-05],"s":[0.6161884,0.6160513,0.6161871],"c":[0.6666667,0.6666667,0.6666667],"b":["when starts then is hp = 125","when any part hit then is hp -= 1","when any part hitting ironpic then is hp -= 5","when is hp <= 0 then destroy all parts with uncollidable 0.5 shrink 120 restore burst 2 force","when any part hit then play pick axe","when is hp <= 0 then play bricks fall collision","when any part hitting magicpic then is hp -= 25"],"t1":{"c":[0,0,0],"x":0.5,"y":0.5,"a":0.8925,"m":0,"n":0,"r":0,"g":0,"o":0.5,"t":0.5,"e":0.5}}]},{"b":156,"t1":43,"s":[{"p":[0.3078973,-0.03500071,-0.5419475],"r":[1.001791E-05,90,-1.001791E-05],"s":[0.8939399,0.8939132,0.8939323],"c":[0.6666667,0.6666667,0.6666667],"b":["when is hp <= 0 then emit stone with 0"],"t1":{"c":[0,0,0],"x":0.5,"y":0.5,"a":0.8925,"m":0,"n":0,"r":0,"g":0,"o":0.5,"t":0.5,"e":0.5}}]},{"b":156,"t1":43,"s":[{"p":[0.2523992,1.555102,-0.3352879],"r":[1.001791E-05,90,-1.221333E-12],"s":[0.3866796,0.3865814,0.3866632],"c":[0.6666667,0.6666667,0.6666667],"b":["when is hp <= 0 then emit stone with 0"],"t1":{"c":[0,0,0],"x":0.5,"y":0.5,"a":0.8925,"m":0,"n":0,"r":0,"g":0,"o":0.5,"t":0.5,"e":0.5}}]},{"b":9,"t":11,"s":[{"p":[0.001055725,0.8372996,0.0862279],"r":[270,90,0],"s":[0.1250072,0.1250098,0.1250044],"c":[1,0.6857142,0],"b":["when is hp <= 0 then emit copper with 0"]}]},{"b":9,"t":11,"s":[{"p":[0.02127826,0.7520086,-0.8595983],"r":[270,9.659345E-06,0],"s":[0.1250302,0.1250268,0.1250277],"c":[1,0.6857142,0],"b":["when is hp <= 0 then emit copper with 0"]}]},{"b":9,"t":11,"s":[{"p":[0.7404349,1.222172,-0.7082483],"r":[270,270,0],"s":[0.1250495,0.1250357,0.1250368],"c":[1,0.6857142,0],"b":["when is hp <= 0 then emit copper with 0"]}]}]}