{"v":9,"a":[5,7,18,48,49],"p":[{"i":[{"t":"6132d6017acabe15181b8ad4","p":[-0.03076173,-0.04048157,-1.888964],"r":[90,-9.659346E-06,0]}],"s":[{"p":[0,0,0],"r":[0,0,0],"s":[0.1750119,0.175009,0.1750111],"c":[1,1,1],"b":["when told by nearby udoor then become next in 5s, play rumbling with 500 very-low-pitch, play bricks friction with -1.5 octaves"]},{"p":[0,0,-1.589956],"r":[0,0,-8.537737E-06],"s":[0.1750254,0.1750236,0.175026],"c":[1,1,1],"b":["when starts then become next in 30s"]},{"p":[0,0,-1.589956],"r":[0,0,-8.537737E-06],"s":[0.1750254,0.1750236,0.175026],"c":[1,1,1],"b":["when starts then become previous in 30s"]}]}]}